{
  "name": "pf1-fr",
  "title": "Pathfinder 1 - Improvements for french (BETA)",
  "description": "(BETA) Improves the system for french speakers. Provides compendiums in French. <p> *** Rejoignez la communauté Discord FR :<a href='https://discord.gg/pPSDNJk'> https://discord.gg/pPSDNJk </a></p>",
  "version": "1.2.2",
  "author": "Sven Werlen",
  "scripts": ["scripts/yaml.min.js", "scripts/importer.js", "scripts/loaddata.js"],
  "systems": ["pf1"],
  "styles": ["style.css"],
  "packs": [
    {
      "name": "classesfr",
      "label": "Classes",
      "system": "pf1",
      "path": "./packs/classes-fr.db",
      "entity": "Item"
    },
    {
      "name": "spellsfr",
      "label": "Sorts",
      "system": "pf1",
      "path": "./packs/spells-fr.db",
      "entity": "Item"
    },
    {
      "name": "featsfr",
      "label": "Dons",
      "system": "pf1",
      "path": "./packs/feats-fr.db",
      "entity": "Item"
    },
    {
      "name": "classfeaturesfr",
      "label": "Aptitudes",
      "system": "pf1",
      "path": "./packs/classfeatures-fr.db",
      "entity": "Item"
    },
    {
      "name": "weaponsfr",
      "label": "Armes",
      "system": "pf1",
      "path": "./packs/weapons-fr.db",
      "entity": "Item"
    },
    {
      "name": "armorsfr",
      "label": "Armures et boucliers",
      "system": "pf1",
      "path": "./packs/armors-fr.db",
      "entity": "Item"
    },
    {
      "name": "equipmentfr",
      "label": "Marchandises et services",
      "system": "pf1",
      "path": "./packs/equipment-fr.db",
      "entity": "Item"
    },
    {
      "name": "tradegoodsfr",
      "label": "Produits de consommation",
      "system": "pf1",
      "path": "./packs/tradegoods-fr.db",
      "entity": "Item"
    },
    {
      "name": "potions",
      "label": "Potions",
      "system": "pf1",
      "path": "./packs/potions-fr.db",
      "entity": "Item"
    },
    {
      "name": "magicfr",
      "label": "Objets magiques",
      "system": "pf1",
      "path": "./packs/magic-fr.db",
      "entity": "Item"
    },
    {
      "name": "bestiaryfr",
      "label": "Bestiaire",
      "system": "pf1",
      "path": "./packs/bestiary-fr.db",
      "entity": "Actor"
    }
  ],
  "url": "https://github.com/SvenWerlen/foundryvtt-pathfinder1-fr",
  "download": "https://github.com/SvenWerlen/foundryvtt-pathfinder1-fr/archive/v-1.2.2.zip",
  "manifest": "https://raw.githubusercontent.com/SvenWerlen/foundryvtt-pathfinder1-fr/master/module.json",
  "minimumCoreVersion": "0.6.0",
  "compatibleCoreVersion": "1.0.0"
}
